nompy/__init__.py
nompy/gender_predictor.py
nompy/name_gender_pb2.py
nompy-0.0.2.dist-info/METADATA
nompy-0.0.2.dist-info/WHEEL
nompy-0.0.2.dist-info/top_level.txt
nompy-0.0.2.dist-info/RECORD
